streamGauge/__init__.py
streamGauge/frontend/build/asset-manifest.json
streamGauge/frontend/build/bootstrap.min.css
streamGauge/frontend/build/index.html
streamGauge/frontend/build/static/js/main.649464f7.js
streamGauge/frontend/build/static/js/main.649464f7.js.LICENSE.txt
streamGauge/frontend/build/static/js/main.649464f7.js.map
StreamGauge-1.0.0.dist-info/LICENSE
StreamGauge-1.0.0.dist-info/METADATA
StreamGauge-1.0.0.dist-info/WHEEL
StreamGauge-1.0.0.dist-info/top_level.txt
StreamGauge-1.0.0.dist-info/RECORD
