Metadata-Version: 2.1
Name: StreamGauge
Version: 1.0.0
Summary: Gauge Chart
Home-page: https://www.techbyderek.com/
Author: Derek Evans
Author-email: derek.evans@deinfoservice.com
Requires-Python: >=3.7
License-File: LICENSE
Requires-Dist: streamlit >=0.63
Requires-Dist: plotly
Requires-Dist: pathlib
Provides-Extra: devel
Requires-Dist: wheel ; extra == 'devel'
Requires-Dist: pytest ; extra == 'devel'
Requires-Dist: playwright ; extra == 'devel'
Requires-Dist: requests ; extra == 'devel'
